LICENSE
MANIFEST.in
README.md
cachet.py
setup.py
cachet.egg-info/PKG-INFO
cachet.egg-info/SOURCES.txt
cachet.egg-info/dependency_links.txt
cachet.egg-info/requires.txt
cachet.egg-info/top_level.txt