Metadata-Version: 1.0
Name: cachet
Version: 0.1.1
Summary: Python client library for the Cachet API
Home-page: https://github.com/imlonghao/cachet.python
Author: imlonghao
Author-email: shield@fastmail.com
License: MIT
Platform: any
